{"key":"event-cat-day","count":60,"images":[{"id":"1834409","url":"https://cdn.pixabay.com/photo/2016/11/18/13/15/animal-1834409_1280.jpg","thumb":"https://cdn.pixabay.com/photo/2016/11/18/13/15/animal-1834409_640.jpg","w":4000,"h":2604,"tags":"animal, cat, eyes, feline, pet, nature, cat's eyes, kitty, kitten, close up, macro, domestic cat","author":"Pexels"},{"id":"502575","url":"https://cdn.pixabay.com/photo/2014/10/25/13/54/willow-catkin-502575_1280.jpg","thumb":"https://cdn.pixabay.com/photo/2014/10/25/13/54/willow-catkin-502575_640.jpg","w":3100,"h":2073,"tags":"willow catkin, spring, bees, pasture, pollen, insect, pollinate, close up, nature, macro, bloom, kitten","author":"congerdesign"},{"id":"8267220","url":"https://cdn.pixabay.com/photo/2023/09/21/17/05/european-shorthair-8267220_1280.jpg","thumb":"https://cdn.pixabay.com/photo/2023/09/21/17/05/european-shorthair-8267220_640.jpg","w":6000,"h":4000,"tags":"european shorthair, cat, kitten, domestic animal, pet, young cat, animal, domestic cat, nature, mammal, close up, feline","author":"guvo59"},{"id":"7226671","url":"https://cdn.pixabay.com/photo/2022/05/28/06/39/cat-7226671_1280.jpg","thumb":"https://cdn.pixabay.com/photo/2022/05/28/06/39/cat-7226671_640.jpg","w":4272,"h":2848,"tags":"cat, kitten, pet, nature, animal, feline, close up","author":"IlonaBurschl"},{"id":"8579018","url":"https://cdn.pixabay.com/photo/2024/02/17/09/39/cat-8579018_1280.jpg","thumb":"https://cdn.pixabay.com/photo/2024/02/17/09/39/cat-8579018_640.jpg","w":5331,"h":3476,"tags":"cat, kitten, animal, nature, tomcat, home, feline, pet","author":"dobrefotki_pl"},{"id":"8611246","url":"https://cdn.pixabay.com/photo/2024/03/03/20/44/cat-8611246_1280.jpg","thumb":"https://cdn.pixabay.com/photo/2024/03/03/20/44/cat-8611246_640.jpg","w":5363,"h":3575,"tags":"cat, domestic cat, nature, animal, domestic animal, pet, feline, kitten","author":"Pezibear"},{"id":"7108080","url":"https://cdn.pixabay.com/photo/2022/04/03/05/22/cat-7108080_1280.jpg","thumb":"https://cdn.pixabay.com/photo/2022/04/03/05/22/cat-7108080_640.jpg","w":3872,"h":2592,"tags":"cat, kitten, pet, young cat, nature, stray cat, street cat, feral cat, animal, domestic cat, blue eyes, feline, mammal, close up","author":"Z3RAJIRAIYA"},{"id":"7641595","url":"https://cdn.pixabay.com/photo/2022/12/07/17/12/cat-7641595_1280.jpg","thumb":"https://cdn.pixabay.com/photo/2022/12/07/17/12/cat-7641595_640.jpg","w":5184,"h":3456,"tags":"cat, nature, kitten, feline, pet, close up, domestic animal, animal, fur, european shorthair","author":"guvo59"},{"id":"7386805","url":"https://cdn.pixabay.com/photo/2022/08/14/23/42/kitten-7386805_1280.jpg","thumb":"https://cdn.pixabay.com/photo/2022/08/14/23/42/kitten-7386805_640.jpg","w":6000,"h":4000,"tags":"kitten, whiskers, curious, domestic animal, young, playful, close up, relaxation","author":"WFranz"},{"id":"1838922","url":"https://cdn.pixabay.com/photo/2016/11/19/12/04/animal-1838922_1280.jpg","thumb":"https://cdn.pixabay.com/photo/2016/11/19/12/04/animal-1838922_640.jpg","w":4993,"h":4000,"tags":"animal, cat, close-up, feline, nature, kitten, pet","author":"Pexels"},{"id":"4523836","url":"https://cdn.pixabay.com/photo/2019/10/03/16/39/cat-4523836_1280.jpg","thumb":"https://cdn.pixabay.com/photo/2019/10/03/16/39/cat-4523836_640.jpg","w":6000,"h":4000,"tags":"cat, animal, pet, wildlife, nature, kitten, close up","author":"Elentyce"},{"id":"2411587","url":"https://cdn.pixabay.com/photo/2017/06/17/09/07/cat-2411587_1280.jpg","thumb":"https://cdn.pixabay.com/photo/2017/06/17/09/07/cat-2411587_640.jpg","w":6000,"h":4000,"tags":"cat, animal, domestic animal, nature, young cat, cute cat, up close, close up, pet, kitten","author":"TillVoigt"},{"id":"2441312","url":"https://cdn.pixabay.com/photo/2017/06/25/17/17/cat-2441312_1280.jpg","thumb":"https://cdn.pixabay.com/photo/2017/06/25/17/17/cat-2441312_640.jpg","w":5166,"h":2053,"tags":"cat, red, mackerel, cute, animal, close up, domestic animal, kitten, pet, red cat","author":"Alexas_Fotos"},{"id":"7106942","url":"https://cdn.pixabay.com/photo/2022/04/02/12/46/cat-7106942_1280.jpg","thumb":"https://cdn.pixabay.com/photo/2022/04/02/12/46/cat-7106942_640.jpg","w":8000,"h":4500,"tags":"cat, pet, feline, nature, animal, mammal, kitten, close up, lounging cat","author":"moshehar"},{"id":"3553106","url":"https://cdn.pixabay.com/photo/2018/07/21/17/53/cat-3553106_1280.jpg","thumb":"https://cdn.pixabay.com/photo/2018/07/21/17/53/cat-3553106_640.jpg","w":3010,"h":1997,"tags":"cat, nature, eyes, tabby, pet, ginger, feline, adorable, kitten, animal","author":"Alexas_Fotos"},{"id":"7106945","url":"https://cdn.pixabay.com/photo/2022/04/02/12/46/sleeping-cat-7106945_1280.jpg","thumb":"https://cdn.pixabay.com/photo/2022/04/02/12/46/sleeping-cat-7106945_640.jpg","w":8000,"h":4500,"tags":"sleeping cat, pet, feline, cat, animal, mammal, nature, kitten, close up, lounging cat","author":"moshehar"},{"id":"7106947","url":"https://cdn.pixabay.com/photo/2022/04/02/12/46/cat-7106947_1280.jpg","thumb":"https://cdn.pixabay.com/photo/2022/04/02/12/46/cat-7106947_640.jpg","w":8000,"h":4500,"tags":"cat, pet, feline, nature, animal, mammal, kitten, close up, lounging cat","author":"moshehar"},{"id":"8267244","url":"https://cdn.pixabay.com/photo/2023/09/21/17/10/european-shorthair-8267244_1280.jpg","thumb":"https://cdn.pixabay.com/photo/2023/09/21/17/10/european-shorthair-8267244_640.jpg","w":6000,"h":4000,"tags":"european shorthair, pet, cat, kitten, domestic animal, young cat, nature, animal, domestic cat, mammal, close up, feline","author":"guvo59"},{"id":"7106944","url":"https://cdn.pixabay.com/photo/2022/04/02/12/46/cat-7106944_1280.jpg","thumb":"https://cdn.pixabay.com/photo/2022/04/02/12/46/cat-7106944_640.jpg","w":8000,"h":4500,"tags":"cat, pet, feline, nature, animal, mammal, kitten, close up, lounging cat","author":"moshehar"},{"id":"2829276","url":"https://cdn.pixabay.com/photo/2017/10/08/09/31/cat-2829276_1280.jpg","thumb":"https://cdn.pixabay.com/photo/2017/10/08/09/31/cat-2829276_640.jpg","w":6000,"h":4000,"tags":"cat, eyes, looking, close up, animal, kitten, nature, pet, stray","author":"dimitrisvetsikas1969"},{"id":"7106946","url":"https://cdn.pixabay.com/photo/2022/04/02/12/46/cat-7106946_1280.jpg","thumb":"https://cdn.pixabay.com/photo/2022/04/02/12/46/cat-7106946_640.jpg","w":8000,"h":4500,"tags":"cat, nature, pet, feline, animal, mammal, kitten, close up, lounging cat","author":"moshehar"},{"id":"7402822","url":"https://cdn.pixabay.com/photo/2022/08/22/05/28/cat-7402822_1280.jpg","thumb":"https://cdn.pixabay.com/photo/2022/08/22/05/28/cat-7402822_640.jpg","w":4737,"h":3607,"tags":"cat, feline, kitten, nature, animal, pet, pets, outdoor, focus, close up, lovely","author":"gdmoonkiller"},{"id":"7559077","url":"https://cdn.pixabay.com/photo/2022/10/31/06/32/european-shorthair-7559077_1280.jpg","thumb":"https://cdn.pixabay.com/photo/2022/10/31/06/32/european-shorthair-7559077_640.jpg","w":5472,"h":3648,"tags":"european shorthair, cat, kitten, domestic animal, animal, domestic cat, mammal, nature, close up, pet, feline","author":"guvo59"},{"id":"3062647","url":"https://cdn.pixabay.com/photo/2018/01/05/11/02/cat-3062647_1280.jpg","thumb":"https://cdn.pixabay.com/photo/2018/01/05/11/02/cat-3062647_640.jpg","w":5659,"h":3773,"tags":"cat, cute, animal, mammal, pet, fur, kitten, domestic animal, eye, lazing around, close up, nature, domestic cat, gray, black, siam, burma, cuddle, white","author":"Lohrelei"},{"id":"7559113","url":"https://cdn.pixabay.com/photo/2022/10/31/07/16/european-shorthair-7559113_1280.jpg","thumb":"https://cdn.pixabay.com/photo/2022/10/31/07/16/european-shorthair-7559113_640.jpg","w":5472,"h":3648,"tags":"european shorthair, cat, nature, pet, kitten, domestic animal, animal, domestic cat, mammal, close up, feline","author":"guvo59"},{"id":"7566767","url":"https://cdn.pixabay.com/photo/2022/11/03/06/41/european-shorthair-7566767_1280.jpg","thumb":"https://cdn.pixabay.com/photo/2022/11/03/06/41/european-shorthair-7566767_640.jpg","w":6000,"h":4000,"tags":"european shorthair, cat, kitten, domestic animal, animal, domestic, mammal, pet, nature, close up, small, young, putty, to play","author":"guvo59"},{"id":"2539855","url":"https://cdn.pixabay.com/photo/2017/07/25/22/59/cat-2539855_1280.jpg","thumb":"https://cdn.pixabay.com/photo/2017/07/25/22/59/cat-2539855_640.jpg","w":4592,"h":3056,"tags":"cat, gray, nature, cute, animal, grass, summer, kitten, sweet, pet, garden, landscape, close up, eyes, nice","author":"Dimhou"},{"id":"7555594","url":"https://cdn.pixabay.com/photo/2022/10/29/16/10/european-shorthair-7555594_1280.jpg","thumb":"https://cdn.pixabay.com/photo/2022/10/29/16/10/european-shorthair-7555594_640.jpg","w":6000,"h":4000,"tags":"european shorthair, cat, kitten, domestic animal, animal, domestic, nature, mammal, close up, feline, pet","author":"guvo59"},{"id":"7393535","url":"https://cdn.pixabay.com/photo/2022/08/17/21/30/cats-7393535_1280.jpg","thumb":"https://cdn.pixabay.com/photo/2022/08/17/21/30/cats-7393535_640.jpg","w":6000,"h":4001,"tags":"cats, kitten, nature, domestic animal, young cat, animal, mammal, whiskers, curious, young, playful, close up, relaxation","author":"WFranz"},{"id":"7386809","url":"https://cdn.pixabay.com/photo/2022/08/14/23/48/cat-7386809_1280.jpg","thumb":"https://cdn.pixabay.com/photo/2022/08/14/23/48/cat-7386809_640.jpg","w":6000,"h":4000,"tags":"cat, animal, kitten, whiskers, curious, pet, domestic animal, young, close up, relaxation, outside","author":"WFranz"},{"id":"4035665","url":"https://cdn.pixabay.com/photo/2019/03/05/06/49/wink-4035665_1280.jpg","thumb":"https://cdn.pixabay.com/photo/2019/03/05/06/49/wink-4035665_640.jpg","w":6016,"h":4000,"tags":"wink, funny, cat, mackerel, red, pet, domestic cat, kitten, hd wallpaper, animal, brown cat, brown funny, brown wallpaper, brown pets","author":"Alexas_Fotos"},{"id":"2739073","url":"https://cdn.pixabay.com/photo/2017/09/11/13/59/cat-2739073_1280.jpg","thumb":"https://cdn.pixabay.com/photo/2017/09/11/13/59/cat-2739073_640.jpg","w":3500,"h":3096,"tags":"kitty, animal, furry, cute, close-up, cat eyes, grey, nature, cat's eye, kitten, house cat","author":"azazelok"},{"id":"2903812","url":"https://cdn.pixabay.com/photo/2017/10/30/23/26/kitty-2903812_1280.jpg","thumb":"https://cdn.pixabay.com/photo/2017/10/30/23/26/kitty-2903812_640.jpg","w":2048,"h":1370,"tags":"kitty, push, nature, cat, pet, kitten, cute, white, animal","author":"Firmanamff"},{"id":"8119896","url":"https://cdn.pixabay.com/photo/2023/07/11/08/49/cat-8119896_1280.jpg","thumb":"https://cdn.pixabay.com/photo/2023/07/11/08/49/cat-8119896_640.jpg","w":6000,"h":4000,"tags":"cat, animal, feline, pet, outdoors, nature, domestic cat","author":"ELG21"},{"id":"5894170","url":"https://cdn.pixabay.com/photo/2021/01/06/11/37/squirrel-5894170_1280.jpg","thumb":"https://cdn.pixabay.com/photo/2021/01/06/11/37/squirrel-5894170_640.jpg","w":6000,"h":4000,"tags":"squirrel, rodent, foraging, eating, wildlife, forest, wilderness, nature, animal, animal world, verifiable kitten, nager, forest animal, wildlife photography, close up, squirrel, squirrel, squirrel, squirrel, squirrel, rodent, nature, wildlife photography","author":"RGY23"},{"id":"7393522","url":"https://cdn.pixabay.com/photo/2022/08/17/21/25/cat-7393522_1280.jpg","thumb":"https://cdn.pixabay.com/photo/2022/08/17/21/25/cat-7393522_640.jpg","w":6000,"h":3999,"tags":"cat, nature, kitten, domestic animal, young cat, animal, domestic, mammal, whiskers, pet, curious, young, playful, close up","author":"WFranz"},{"id":"1614345","url":"https://cdn.pixabay.com/photo/2016/08/23/13/25/cat-1614345_1280.jpg","thumb":"https://cdn.pixabay.com/photo/2016/08/23/13/25/cat-1614345_640.jpg","w":4758,"h":3172,"tags":"cat, domestic cat, domestic animal, kitten, animal, pet, puss, close up","author":"herbert2512"},{"id":"7393500","url":"https://cdn.pixabay.com/photo/2022/08/17/21/18/cat-7393500_1280.jpg","thumb":"https://cdn.pixabay.com/photo/2022/08/17/21/18/cat-7393500_640.jpg","w":6000,"h":4001,"tags":"cat, kitten, young cat, domestic animal, animal, mammal, nature, whiskers, curious, young, pet, playful, close up","author":"WFranz"},{"id":"7555595","url":"https://cdn.pixabay.com/photo/2022/10/29/16/11/european-shorthair-7555595_1280.jpg","thumb":"https://cdn.pixabay.com/photo/2022/10/29/16/11/european-shorthair-7555595_640.jpg","w":6000,"h":4000,"tags":"european shorthair, nature, cat, kitten, domestic animal, animal, domestic, mammal, close up, feline, pet","author":"guvo59"},{"id":"7290383","url":"https://cdn.pixabay.com/photo/2022/06/28/19/01/animal-7290383_1280.jpg","thumb":"https://cdn.pixabay.com/photo/2022/06/28/19/01/animal-7290383_640.jpg","w":5779,"h":3842,"tags":"animal, mammal, cat, mackerel, pet, tabby cat, kitten, nature, puss, fur, whiskers","author":"Alexas_Fotos"},{"id":"1328470","url":"https://cdn.pixabay.com/photo/2016/04/14/08/48/cat-1328470_1280.jpg","thumb":"https://cdn.pixabay.com/photo/2016/04/14/08/48/cat-1328470_640.jpg","w":5632,"h":4224,"tags":"cat, animal, cat close up, pet, kitten, feline, eyes, kitty","author":"kayobellis"},{"id":"7340678","url":"https://cdn.pixabay.com/photo/2022/07/23/22/15/maine-coon-7340678_1280.jpg","thumb":"https://cdn.pixabay.com/photo/2022/07/23/22/15/maine-coon-7340678_640.jpg","w":5472,"h":3648,"tags":"maine coon, cat, domestic animal, pet, nature, animal, kitten, mammal, domestic cat, close up","author":"VBlock"},{"id":"7559063","url":"https://cdn.pixabay.com/photo/2022/10/31/06/15/european-shorthair-7559063_1280.jpg","thumb":"https://cdn.pixabay.com/photo/2022/10/31/06/15/european-shorthair-7559063_640.jpg","w":5472,"h":3648,"tags":"european shorthair, cat, pet, nature, kitten, domestic animal, animal, domestic cat, mammal, close up, feline","author":"guvo59"},{"id":"8228962","url":"https://cdn.pixabay.com/photo/2023/09/02/14/10/squirrel-8228962_1280.jpg","thumb":"https://cdn.pixabay.com/photo/2023/09/02/14/10/squirrel-8228962_640.jpg","w":6000,"h":4000,"tags":"squirrel, oak kitten, calibration hangover, european, flying squirrel, rodent, nature, tree squirrel, croissant, close up, sciurus, eurasian, tree trunk, animal, fauna, bokeh","author":"Nennieinszweidrei"},{"id":"3808564","url":"https://cdn.pixabay.com/photo/2018/11/11/11/33/cat-3808564_1280.jpg","thumb":"https://cdn.pixabay.com/photo/2018/11/11/11/33/cat-3808564_640.jpg","w":3984,"h":2656,"tags":"cat, animal, cats, cute, kitten, nature, animals, close up, tame, pet, homemade","author":"SlowCZECH"},{"id":"166450","url":"https://cdn.pixabay.com/photo/2013/07/23/23/23/cat-166450_1280.jpg","thumb":"https://cdn.pixabay.com/photo/2013/07/23/23/23/cat-166450_640.jpg","w":3888,"h":2592,"tags":"cat, paws, leg, fur, close-up, animal, nature, white, pet, kitten, feline","author":"PDPics"},{"id":"7037987","url":"https://cdn.pixabay.com/photo/2022/02/27/20/05/squirrel-7037987_1280.jpg","thumb":"https://cdn.pixabay.com/photo/2022/02/27/20/05/squirrel-7037987_640.jpg","w":3000,"h":3000,"tags":"squirrel, rodent, wildlife, forest, wilderness, nature, animal, animal world, verifiable kitten, nager, forest animal, wildlife photography, close up","author":"Johnny_Harvester"},{"id":"7569227","url":"https://cdn.pixabay.com/photo/2022/11/04/07/35/european-shorthair-7569227_1280.jpg","thumb":"https://cdn.pixabay.com/photo/2022/11/04/07/35/european-shorthair-7569227_640.jpg","w":6000,"h":4000,"tags":"european shorthair, cat, kitten, domestic animal, animal, domestic, mammal, nature, close up, small, young, pet, putty, to play","author":"guvo59"},{"id":"6538883","url":"https://cdn.pixabay.com/photo/2021/08/11/16/02/squirrel-6538883_1280.jpg","thumb":"https://cdn.pixabay.com/photo/2021/08/11/16/02/squirrel-6538883_640.jpg","w":4320,"h":3456,"tags":"squirrel, rodent, wildlife, forest, wilderness, nature, animal, animal world, verifiable kitten, nager, forest animal, wildlife photography, close up","author":"valentinhintikka"},{"id":"7569229","url":"https://cdn.pixabay.com/photo/2022/11/04/07/35/european-shorthair-7569229_1280.jpg","thumb":"https://cdn.pixabay.com/photo/2022/11/04/07/35/european-shorthair-7569229_640.jpg","w":6000,"h":4000,"tags":"european shorthair, cat, pet, kitten, nature, domestic animal, animal, domestic, mammal, close up, small, young, putty, to play","author":"guvo59"},{"id":"7569232","url":"https://cdn.pixabay.com/photo/2022/11/04/07/36/european-shorthair-7569232_1280.jpg","thumb":"https://cdn.pixabay.com/photo/2022/11/04/07/36/european-shorthair-7569232_640.jpg","w":6000,"h":4000,"tags":"european shorthair, cat, kitten, domestic animal, animal, domestic, pet, nature, mammal, close up, small, young, putty, to play","author":"guvo59"},{"id":"3399108","url":"https://cdn.pixabay.com/photo/2018/05/14/09/16/cat-3399108_1280.jpg","thumb":"https://cdn.pixabay.com/photo/2018/05/14/09/16/cat-3399108_640.jpg","w":6000,"h":4000,"tags":"cat, animal, domestic animal, young cat, curious, cub, creature, playful, pet, mammal, cat eyes, nature, close up, kitten","author":"anncapictures"},{"id":"3519551","url":"https://cdn.pixabay.com/photo/2018/07/06/01/16/cat-3519551_1280.jpg","thumb":"https://cdn.pixabay.com/photo/2018/07/06/01/16/cat-3519551_640.jpg","w":4752,"h":3168,"tags":"cat, white, kitten, domestic animal, cute, animal, fur, pet, eyes, young, close up, table tennis table","author":"Matthias_Lemm"},{"id":"6627188","url":"https://cdn.pixabay.com/photo/2021/09/15/15/46/squirrel-6627188_1280.jpg","thumb":"https://cdn.pixabay.com/photo/2021/09/15/15/46/squirrel-6627188_640.jpg","w":5184,"h":3456,"tags":"squirrel, rodent, foraging, eating, wildlife, forest, wilderness, nature, animal, animal world, verifiable kitten, nager, forest animal, wildlife photography, close up","author":"valentinhintikka"},{"id":"7386816","url":"https://cdn.pixabay.com/photo/2022/08/15/00/00/cat-7386816_1280.jpg","thumb":"https://cdn.pixabay.com/photo/2022/08/15/00/00/cat-7386816_640.jpg","w":6001,"h":4000,"tags":"cat, kitten, pet, young cat, animal, domestic, feline, mammal, whiskers, curious, domestic animal, young, nature, playful, close up, relaxation","author":"WFranz"},{"id":"7291825","url":"https://cdn.pixabay.com/photo/2022/06/29/13/49/squirrel-7291825_1280.jpg","thumb":"https://cdn.pixabay.com/photo/2022/06/29/13/49/squirrel-7291825_640.jpg","w":4566,"h":3040,"tags":"squirrel, oak kitten, rodent, meal, wildlife, nature, animal, forest animal","author":"Ralphs_Fotos"},{"id":"1378362","url":"https://cdn.pixabay.com/photo/2016/05/07/22/39/cat-1378362_1280.jpg","thumb":"https://cdn.pixabay.com/photo/2016/05/07/22/39/cat-1378362_640.jpg","w":2000,"h":1107,"tags":"cat, eye, close up, british shorthair, thoroughbred, fur, pet, brown, beige, blue eyes, cute, animal, puss, kitten","author":"Alexas_Fotos"},{"id":"7386819","url":"https://cdn.pixabay.com/photo/2022/08/15/00/04/cat-7386819_1280.jpg","thumb":"https://cdn.pixabay.com/photo/2022/08/15/00/04/cat-7386819_640.jpg","w":6000,"h":4000,"tags":"cat, kitten, pet, young cat, animal, domestic, feline, mammal, whiskers, curious, domestic animal, young, playful, nature, close up, relaxation","author":"WFranz"},{"id":"4396242","url":"https://cdn.pixabay.com/photo/2019/08/10/05/52/cat-4396242_1280.jpg","thumb":"https://cdn.pixabay.com/photo/2019/08/10/05/52/cat-4396242_640.jpg","w":6000,"h":4000,"tags":"cat, small, kitten, head, black, white, close up, beard, view, ears, cute, pet, domestic animal, animal, domestic cat, infant, mammal","author":"birgl"},{"id":"1279066","url":"https://cdn.pixabay.com/photo/2016/03/25/15/56/cat-1279066_1280.jpg","thumb":"https://cdn.pixabay.com/photo/2016/03/25/15/56/cat-1279066_640.jpg","w":2977,"h":1760,"tags":"cat, lurk, animal, frog, fear, hide, domestic animal, puss, kitten, mackerel, pet, hidden, cute, cat eyes, fun, tiger cat, close up, ambush","author":"Alexas_Fotos"}]}